LICENSE
MANIFEST.in
README.rst
setup.cfg
setup.py
Hemp.egg-info/PKG-INFO
Hemp.egg-info/SOURCES.txt
Hemp.egg-info/dependency_links.txt
Hemp.egg-info/entry_points.txt
Hemp.egg-info/requires.txt
Hemp.egg-info/top_level.txt
hemp/__init__.py
hemp/api.py
hemp/gitutils.py
hemp/main.py
hemp/release.py
hemp/workspace.py
hemp/internal/__init__.py
hemp/internal/hempfile.py
hemp/internal/utils.py
hemp/tasks/__init__.py
hemp/tasks/stage.py