Metadata-Version: 1.1
Name: Hemp
Version: 0.1.5
Summary: Tools for Fabric
Home-page: https://github.com/Addvilz/hemp
Author: Addvilz
Author-email: mrtreinis@gmail.com
License: Apache 2.0
Download-URL: https://github.com/Addvilz/hemp
Platform: UNIX
Classifier: Development Status :: 4 - Beta
Classifier: Environment :: Console
Classifier: Intended Audience :: Developers
Classifier: Intended Audience :: System Administrators
Classifier: License :: OSI Approved :: Apache Software License
Classifier: Operating System :: MacOS :: MacOS X
Classifier: Operating System :: POSIX :: Linux
Classifier: Operating System :: POSIX
Classifier: Operating System :: Unix
Classifier: Programming Language :: Python :: 2.7
Classifier: Programming Language :: Python
Classifier: Topic :: Software Development :: Build Tools
Classifier: Topic :: Software Development :: Libraries :: Python Modules
Classifier: Topic :: Software Development :: Libraries
Classifier: Topic :: Software Development
Classifier: Topic :: System :: Software Distribution
Classifier: Topic :: System :: Systems Administration
